README.rst
setup.py
passotp/__init__.py
passotp.egg-info/PKG-INFO
passotp.egg-info/SOURCES.txt
passotp.egg-info/dependency_links.txt
passotp.egg-info/entry_points.txt
passotp.egg-info/requires.txt
passotp.egg-info/top_level.txt