Metadata-Version: 1.0
Name: passotp
Version: 0.3.0
Summary: A TOTP cli for Pass
Home-page: https://github.com/felipelerena/passotp/
Author: Felipe Lerena
Author-email: felipelerena@gmail.com
License: GPLv3
Platform: UNKNOWN
